testwizard/testobjects_core/TestObjectBase.py
testwizard/testobjects_core/__init__.py
testwizard/testobjects_core/models/AudioInfo.py
testwizard/testobjects_core/models/CustomProperties.py
testwizard/testobjects_core/models/DeviceInfo.py
testwizard/testobjects_core/models/MobileInfo.py
testwizard/testobjects_core/models/RemoteControlInfo.py
testwizard/testobjects_core/models/TestObjectInfo.py
testwizard/testobjects_core/models/VendorInfo.py
testwizard/testobjects_core/models/VideoInfo.py
testwizard/testobjects_core/models/__init__.py
testwizard.testobjects_core-3.8.1.dist-info/LICENSE.txt
testwizard.testobjects_core-3.8.1.dist-info/METADATA
testwizard.testobjects_core-3.8.1.dist-info/WHEEL
testwizard.testobjects_core-3.8.1.dist-info/top_level.txt
testwizard.testobjects_core-3.8.1.dist-info/RECORD
